aws_deploy/.gitignore
aws_deploy/__init__.py
aws_deploy/adminer/__init__.py
aws_deploy/adminer/commands.py
aws_deploy/adminer/login.py
aws_deploy/adminer/qrcode_generator.py
aws_deploy/alb.py
aws_deploy/aws_lambda/commands.py
aws_deploy/aws_lambda/create_function.py
aws_deploy/aws_lambda/env_resolver.py
aws_deploy/aws_lambda/source_builder.py
aws_deploy/cli_common.py
aws_deploy/cloudformation/exceptions.py
aws_deploy/cloudformation/parameter/base.py
aws_deploy/cloudformation/parameter/db_password.py
aws_deploy/cloudformation/parameter/exceptions.py
aws_deploy/cloudformation/parameter/general.py
aws_deploy/cloudformation/parameter/resolver.py
aws_deploy/cloudformation/parameter/ssm_stored.py
aws_deploy/cloudformation/parameter_manager.py
aws_deploy/cloudformation/resource_remover.py
aws_deploy/cloudformation/stack.py
aws_deploy/cloudformation/stack_creator.py
aws_deploy/cloudformation/stack_deleter.py
aws_deploy/cloudformation/template.py
aws_deploy/cloudformation/template_factory.py
aws_deploy/cloudformation/template_parser.py
aws_deploy/codepipeline/invoker.py
aws_deploy/config.py
aws_deploy/ec2_op.py
aws_deploy/main.py
aws_deploy/service.py
aws_deploy/utils.py
aws_ecs_deploy-0.1.1.dist-info/LICENSE
aws_ecs_deploy-0.1.1.dist-info/METADATA
aws_ecs_deploy-0.1.1.dist-info/WHEEL
aws_ecs_deploy-0.1.1.dist-info/entry_points.txt
aws_ecs_deploy-0.1.1.dist-info/RECORD
